chat_llm_cli-1.6.0.dist-info/METADATA
chat_llm_cli-1.6.0.dist-info/WHEEL
chat_llm_cli-1.6.0.dist-info/entry_points.txt
chat_llm_cli-1.6.0.dist-info/licenses/LICENSE
chat_llm_cli/.DS_Store
chat_llm_cli/__init__.py
chat_llm_cli/__main__.py
chat_llm_cli/chat_llm_cli.py
chat_llm_cli/config/.DS_Store
chat_llm_cli/config/__init__.py
chat_llm_cli/config/api_key_handler.py
chat_llm_cli/config/config.py
chat_llm_cli/config/model_handler.py
chat_llm_cli/llm_api/__init__.py
chat_llm_cli/llm_api/llm_handler.py
chat_llm_cli/llm_api/ollama_handler.py
chat_llm_cli/logs/__init__.py
chat_llm_cli/logs/loguru_init.py
chat_llm_cli/prompt/.DS_Store
chat_llm_cli/prompt/__init__.py
chat_llm_cli/prompt/custom_console.py
chat_llm_cli/prompt/expenses.py
chat_llm_cli/prompt/history.py
chat_llm_cli/prompt/prompt.py
chat_llm_cli/prompt/prompt_ollama.py
chat_llm_cli-1.6.0.dist-info/RECORD
