Metadata-Version: 2.1
Name: chat_llm_cli
Version: 1.6.0
Summary: Simple yet effective command line client for chatting with big LLMs using the llm_lite wrapper or ollama models
Author-Email: tadeasf <business@tadeasfort.com>
License: MIT
Requires-Python: >=3.12
Requires-Dist: click
Requires-Dist: prompt-toolkit
Requires-Dist: requests
Requires-Dist: rich
Requires-Dist: xdg-base-dirs
Requires-Dist: pyperclip
Requires-Dist: openai
Requires-Dist: loguru
Requires-Dist: litellm
Requires-Dist: pysocks
Requires-Dist: urllib3
Requires-Dist: wcwidth
Requires-Dist: pygments
Requires-Dist: pyyaml
Requires-Dist: platformdirs
Requires-Dist: idna
Requires-Dist: markdown-it-py
Requires-Dist: mdurl
Requires-Dist: pathspec
Requires-Dist: aiohappyeyeballs
Requires-Dist: aiosignal
Requires-Dist: annotated-types
Requires-Dist: anyio
Requires-Dist: attrs
Requires-Dist: certifi
Requires-Dist: charset-normalizer
Requires-Dist: distro
Requires-Dist: filelock
Requires-Dist: frozenlist
Requires-Dist: fsspec
Requires-Dist: h11
Requires-Dist: httpcore
Requires-Dist: httpx
Requires-Dist: huggingface-hub
Requires-Dist: importlib-metadata
Requires-Dist: jinja2
Requires-Dist: jiter
Requires-Dist: jsonschema
Requires-Dist: jsonschema-specifications
Requires-Dist: markupsafe
Requires-Dist: multidict
Requires-Dist: packaging
Requires-Dist: pydantic
Requires-Dist: pydantic-core
Requires-Dist: python-dotenv
Requires-Dist: referencing
Requires-Dist: regex
Requires-Dist: rpds-py
Requires-Dist: sniffio
Requires-Dist: tiktoken
Requires-Dist: tokenizers
Requires-Dist: tqdm
Requires-Dist: typing-extensions
Requires-Dist: yarl
Requires-Dist: zipp
Requires-Dist: typer
Requires-Dist: catppuccin[pygments]
